project/m4/rtl/compute_core.v
// ============================================================================
// compute_core.v — Autoencoder Inference Compute Core (Plain Verilog)
// ============================================================================
// Project : ECE 410/510 HW4AI — Autoencoder Anomaly Detection Accelerator
//
// 8-MAC time-multiplexed forward pass for 4-layer autoencoder:
//   Layer 0: Linear(32->16)+ReLU  Layer 1: Linear(16->8)+ReLU
//   Layer 2: Linear(8->16)+ReLU   Layer 3: Linear(16->32)
// Then MSE + threshold comparison.
//
// Format: INT8 signed weights/activations, 32-bit accumulator, Q8.8 MSE.
// Clock:  Single (clk), posedge. Reset: Active-low async (rst_n).
//
// Ports:
//   clk, rst_n, start, input_data[255:0] (32xINT8 packed),
//   weight_wr_en, weight_wr_addr[10:0], weight_wr_data[7:0],
//   threshold[15:0], anomaly_flag, done, mse_out[15:0]
// ============================================================================

module compute_core (
    input  wire         clk,
    input  wire         rst_n,
    input  wire         start,
    input  wire [255:0] input_data,
    input  wire         weight_wr_en,
    input  wire [10:0]  weight_wr_addr,
    input  wire [7:0]   weight_wr_data,
    input  wire [15:0]  threshold,
    output reg          anomaly_flag,
    output reg          done,
    output reg  [15:0]  mse_out
);

    localparam S_IDLE=3'd0, S_LOAD=3'd1, S_MAC=3'd2, S_BIAS=3'd3, S_MSE=3'd4, S_DONE=3'd5, S_COPY=3'd6;

    // Weight SRAM
    reg [7:0] weight_mem [0:1351];
    always @(posedge clk) begin
        if (weight_wr_en) weight_mem[weight_wr_addr] <= weight_wr_data;
    end

    // Activation storage
    reg [7:0] act_in  [0:31];
    reg [7:0] act_out [0:31];
    reg [7:0] orig_in [0:31];

    // 8 accumulators (explicit, no unpacked array)
    reg signed [31:0] acc0, acc1, acc2, acc3, acc4, acc5, acc6, acc7;

    // State
    reg [2:0]  state;
    reg [1:0]  cur_layer;
    reg [2:0]  cur_round;
    reg [5:0]  mac_idx;
    reg [5:0]  mse_idx;
    reg [31:0] mse_acc;

    // Layer config (combinational)
    reg [5:0]  l_in, l_out;
    reg [10:0] l_wbase, l_bbase;
    reg        l_relu;
    reg [2:0]  l_rounds;

    always @(*) begin
        case (cur_layer)
            2'd0: begin l_in=32; l_out=16; l_wbase=0;   l_bbase=512;  l_relu=1; l_rounds=2; end
            2'd1: begin l_in=16; l_out=8;  l_wbase=528; l_bbase=656;  l_relu=1; l_rounds=1; end
            2'd2: begin l_in=8;  l_out=16; l_wbase=664; l_bbase=792;  l_relu=1; l_rounds=2; end
            default: begin l_in=16; l_out=32; l_wbase=808; l_bbase=1320; l_relu=0; l_rounds=4; end
        endcase
    end

    wire [5:0] nbase = {cur_round, 3'b000};
    wire signed [7:0] a_val = act_in[mac_idx];

    // Weight addresses (8 lanes)
    wire [10:0] wa0=l_wbase+(nbase+0)*l_in+mac_idx;
    wire [10:0] wa1=l_wbase+(nbase+1)*l_in+mac_idx;
    wire [10:0] wa2=l_wbase+(nbase+2)*l_in+mac_idx;
    wire [10:0] wa3=l_wbase+(nbase+3)*l_in+mac_idx;
    wire [10:0] wa4=l_wbase+(nbase+4)*l_in+mac_idx;
    wire [10:0] wa5=l_wbase+(nbase+5)*l_in+mac_idx;
    wire [10:0] wa6=l_wbase+(nbase+6)*l_in+mac_idx;
    wire [10:0] wa7=l_wbase+(nbase+7)*l_in+mac_idx;

    // Bias addresses
    wire [10:0] ba0=l_bbase+nbase+0, ba1=l_bbase+nbase+1;
    wire [10:0] ba2=l_bbase+nbase+2, ba3=l_bbase+nbase+3;
    wire [10:0] ba4=l_bbase+nbase+4, ba5=l_bbase+nbase+5;
    wire [10:0] ba6=l_bbase+nbase+6, ba7=l_bbase+nbase+7;

    // Bias+scale+clamp+ReLU for each lane (combinational)
    reg signed [7:0] r0,r1,r2,r3,r4,r5,r6,r7;
    reg signed [31:0] bv;

    `define BIAS_LANE(ACC, BA, RES) \
        bv = $signed(ACC >>> 7) + $signed({{24{weight_mem[BA][7]}}, weight_mem[BA]}); \
        if (bv > 127) RES = 8'sd127; \
        else if (bv < -128) RES = -8'sd128; \
        else RES = bv[7:0]; \
        if (l_relu && RES[7]) RES = 8'sd0;

    always @(*) begin
        `BIAS_LANE(acc0, ba0, r0)
        `BIAS_LANE(acc1, ba1, r1)
        `BIAS_LANE(acc2, ba2, r2)
        `BIAS_LANE(acc3, ba3, r3)
        `BIAS_LANE(acc4, ba4, r4)
        `BIAS_LANE(acc5, ba5, r5)
        `BIAS_LANE(acc6, ba6, r6)
        `BIAS_LANE(acc7, ba7, r7)
    end

    // MSE diff
    wire signed [8:0] mse_diff = $signed({orig_in[mse_idx][7], orig_in[mse_idx]}) - $signed({act_out[mse_idx][7], act_out[mse_idx]});
    wire [17:0] mse_sq = mse_diff * mse_diff;

    // Main FSM
    integer k;
    always @(posedge clk or negedge rst_n) begin
        if (!rst_n) begin
            state<=S_IDLE; cur_layer<=0; cur_round<=0; mac_idx<=0;
            mse_idx<=0; mse_acc<=0; anomaly_flag<=0; done<=0; mse_out<=0;
            acc0<=0; acc1<=0; acc2<=0; acc3<=0;
            acc4<=0; acc5<=0; acc6<=0; acc7<=0;
            for(k=0;k<32;k=k+1) begin act_in[k]<=0; act_out[k]<=0; orig_in[k]<=0; end
        end else begin
            done <= 1'b0;
            case (state)

            S_IDLE: if (start) begin
                for(k=0;k<32;k=k+1) begin
                    act_in[k]  <= input_data[k*8 +: 8];
                    orig_in[k] <= input_data[k*8 +: 8];
                end
                cur_layer<=0; cur_round<=0; state<=S_LOAD;
            end

            S_LOAD: begin
                acc0<=0; acc1<=0; acc2<=0; acc3<=0;
                acc4<=0; acc5<=0; acc6<=0; acc7<=0;
                mac_idx<=0; state<=S_MAC;
            end

            S_MAC: begin
                acc0<=acc0+$signed(a_val)*$signed(weight_mem[wa0]);
                acc1<=acc1+$signed(a_val)*$signed(weight_mem[wa1]);
                acc2<=acc2+$signed(a_val)*$signed(weight_mem[wa2]);
                acc3<=acc3+$signed(a_val)*$signed(weight_mem[wa3]);
                acc4<=acc4+$signed(a_val)*$signed(weight_mem[wa4]);
                acc5<=acc5+$signed(a_val)*$signed(weight_mem[wa5]);
                acc6<=acc6+$signed(a_val)*$signed(weight_mem[wa6]);
                acc7<=acc7+$signed(a_val)*$signed(weight_mem[wa7]);
                if (mac_idx==l_in-1) state<=S_BIAS;
                else mac_idx<=mac_idx+1;
            end

            S_BIAS: begin
                if(nbase+0<l_out) act_out[nbase+0]<=r0;
                if(nbase+1<l_out) act_out[nbase+1]<=r1;
                if(nbase+2<l_out) act_out[nbase+2]<=r2;
                if(nbase+3<l_out) act_out[nbase+3]<=r3;
                if(nbase+4<l_out) act_out[nbase+4]<=r4;
                if(nbase+5<l_out) act_out[nbase+5]<=r5;
                if(nbase+6<l_out) act_out[nbase+6]<=r6;
                if(nbase+7<l_out) act_out[nbase+7]<=r7;

                if (cur_round==l_rounds-1) begin
                    cur_round<=0;
                    state<=S_COPY;
                end else begin
                    cur_round<=cur_round+1; state<=S_LOAD;
                end
            end

            S_COPY: begin
                for(k=0;k<32;k=k+1) act_in[k]<=act_out[k];
                if (cur_layer==2'd3) begin
                    mse_acc<=0; mse_idx<=0; state<=S_MSE;
                end else begin
                    cur_layer<=cur_layer+1; state<=S_LOAD;
                end
            end

            S_MSE: begin
                mse_acc <= mse_acc + {14'd0, mse_sq};
                if (mse_idx==6'd31) state<=S_DONE;
                else mse_idx<=mse_idx+1;
            end

            S_DONE: begin
                mse_out      <= mse_acc[20:5];
                anomaly_flag <= (mse_acc[20:5] > threshold);
                done         <= 1'b1;
                state        <= S_IDLE;
            end

            default: state <= S_IDLE;
            endcase
        end
    end

endmodule

project/m4/rtl/interface.v
// ============================================================================
// interface.v — AXI4-Stream/Lite Interface (Plain Verilog)
// ============================================================================
// Module: ae_interface
//
// Data path:  AXI4-Stream slave (256-bit input) -> compute_core ->
//             AXI4-Stream master (flag + MSE)
// Config:     Register write/read for weights, threshold, control.
//
// AXI4-Stream: TVALID/TREADY contract honored (ARM IHI 0051A s2.2.1).
//
// Register map:
//   0x0  WEIGHT_DATA [7:0]   WO  Weight byte
//   0x1  WEIGHT_ADDR [10:0]  WO  Weight SRAM address
//   0x2  WEIGHT_WR   [0:0]   WO  Pulse to commit write
//   0x3  THRESHOLD   [15:0]  RW  MSE threshold (Q8.8)
//   0x4  STATUS      [31:0]  RO  [0]=done [1]=anomaly
//   0x5  MSE_OUT     [15:0]  RO  Last MSE
//
// Clock: Single (clk), posedge. Reset: Active-low async (rst_n).
// ============================================================================

module ae_interface (
    input  wire         clk,
    input  wire         rst_n,

    // AXI4-Stream Slave (sensor input, 32 bytes packed)
    input  wire [255:0] s_axis_tdata,
    input  wire         s_axis_tvalid,
    output wire         s_axis_tready,

    // AXI4-Stream Master (result)
    output wire [31:0]  m_axis_tdata,
    output wire         m_axis_tvalid,
    input  wire         m_axis_tready,

    // Config register port
    input  wire [3:0]   cfg_addr,
    input  wire [31:0]  cfg_wdata,
    input  wire         cfg_wr_en,
    output reg  [31:0]  cfg_rdata,
    input  wire         cfg_rd_en
);

    // ── Config registers ────────────────────────────────────────────────
    reg [7:0]  reg_weight_data;
    reg [10:0] reg_weight_addr;
    reg        reg_weight_wr;
    reg [15:0] reg_threshold;

    // ── Core signals ────────────────────────────────────────────────────
    wire        core_done;
    wire        core_anomaly;
    wire [15:0] core_mse;

    // ── Input capture ───────────────────────────────────────────────────
    reg [255:0] captured_input;
    reg         input_ready;
    reg         running;

    assign s_axis_tready = !running;

    // Capture input on AXI4-Stream handshake
    always @(posedge clk or negedge rst_n) begin
        if (!rst_n) begin
            captured_input <= 256'd0;
            input_ready    <= 1'b0;
            running        <= 1'b0;
        end else begin
            input_ready <= 1'b0;
            if (s_axis_tvalid && s_axis_tready) begin
                captured_input <= s_axis_tdata;
                input_ready    <= 1'b1;
                running        <= 1'b1;
            end
            if (core_done)
                running <= 1'b0;
        end
    end

    // ── Compute core ────────────────────────────────────────────────────
    compute_core u_core (
        .clk            (clk),
        .rst_n          (rst_n),
        .start          (input_ready),
        .input_data     (captured_input),
        .weight_wr_en   (reg_weight_wr),
        .weight_wr_addr (reg_weight_addr),
        .weight_wr_data (reg_weight_data),
        .threshold      (reg_threshold),
        .anomaly_flag   (core_anomaly),
        .done           (core_done),
        .mse_out        (core_mse)
    );

    // ── Output holding register ─────────────────────────────────────────
    reg [31:0] out_data;
    reg        out_valid;

    assign m_axis_tdata  = out_data;
    assign m_axis_tvalid = out_valid;

    always @(posedge clk or negedge rst_n) begin
        if (!rst_n) begin
            out_data  <= 32'd0;
            out_valid <= 1'b0;
        end else begin
            if (core_done) begin
                out_data  <= {15'b0, core_mse, core_anomaly};
                out_valid <= 1'b1;
            end else if (m_axis_tready && out_valid) begin
                out_valid <= 1'b0;
            end
        end
    end

    // ── Config write ────────────────────────────────────────────────────
    always @(posedge clk or negedge rst_n) begin
        if (!rst_n) begin
            reg_weight_data <= 8'd0;
            reg_weight_addr <= 11'd0;
            reg_weight_wr   <= 1'b0;
            reg_threshold   <= 16'd256;
        end else begin
            reg_weight_wr <= 1'b0;
            if (cfg_wr_en) begin
                case (cfg_addr)
                    4'h0: reg_weight_data <= cfg_wdata[7:0];
                    4'h1: reg_weight_addr <= cfg_wdata[10:0];
                    4'h2: reg_weight_wr   <= cfg_wdata[0];
                    4'h3: reg_threshold   <= cfg_wdata[15:0];
                    default: ;
                endcase
            end
        end
    end

    // ── Config read ─────────────────────────────────────────────────────
    always @(*) begin
        case (cfg_addr)
            4'h3:    cfg_rdata = {16'b0, reg_threshold};
            4'h4:    cfg_rdata = {30'b0, core_anomaly, core_done};
            4'h5:    cfg_rdata = {16'b0, core_mse};
            default: cfg_rdata = 32'hDEADBEEF;
        endcase
    end

endmodule

project/m3/rtl/top.v
// ============================================================================
// top.v — Integrated Top Module: Autoencoder Anomaly Detection Accelerator
// ============================================================================
// Project : ECE 410/510 HW4AI — Milestone 3
//
// This top module instantiates ae_interface and compute_core, connecting
// them end-to-end. The interface is the ONLY path between the host and
// the compute engine — no direct access to compute_core ports.
//
// Glue logic: None required. ae_interface already instantiates compute_core
// internally and wires all inter-module signals. This top module re-exports
// ae_interface as the system boundary, making the host-facing ports the
// only external interface.
//
// External ports:
//   clk             input   1-bit   System clock (posedge)
//   rst_n           input   1-bit   Active-low async reset
//   s_axis_tdata    input   256-bit AXI4-Stream slave data (32×INT8 sensor)
//   s_axis_tvalid   input   1-bit   AXI4-Stream slave valid
//   s_axis_tready   output  1-bit   AXI4-Stream slave ready (backpressure)
//   m_axis_tdata    output  32-bit  AXI4-Stream master data (MSE + flag)
//   m_axis_tvalid   output  1-bit   AXI4-Stream master valid
//   m_axis_tready   input   1-bit   AXI4-Stream master ready
//   cfg_addr        input   4-bit   Config register address
//   cfg_wdata       input   32-bit  Config register write data
//   cfg_wr_en       input   1-bit   Config register write enable
//   cfg_rdata       output  32-bit  Config register read data
//   cfg_rd_en       input   1-bit   Config register read enable
//
// Data flow:
//   1. Host writes weights via cfg port (addr 0x0-0x2) → SRAM in compute_core
//   2. Host sets threshold via cfg port (addr 0x3)
//   3. Host streams sensor sample via AXI4-Stream slave
//   4. compute_core runs 4-layer forward pass + MSE + threshold compare
//   5. Result (anomaly flag + MSE) appears on AXI4-Stream master
//   6. Host reads status/MSE via cfg port (addr 0x4-0x5) if desired
//
// Architecture:
//   ae_interface contains compute_core as a submodule. The interface handles
//   AXI4-Stream handshaking, config register decoding, and result packaging.
//   No additional glue logic is needed between the two modules.
// ============================================================================

module top (
    input  wire         clk,
    input  wire         rst_n,

    // AXI4-Stream Slave — sensor input (32 bytes packed as 256 bits)
    input  wire [255:0] s_axis_tdata,
    input  wire         s_axis_tvalid,
    output wire         s_axis_tready,

    // AXI4-Stream Master — result output (anomaly flag + MSE)
    output wire [31:0]  m_axis_tdata,
    output wire         m_axis_tvalid,
    input  wire         m_axis_tready,

    // Config register port (AXI4-Lite simplified)
    input  wire [3:0]   cfg_addr,
    input  wire [31:0]  cfg_wdata,
    input  wire         cfg_wr_en,
    output wire [31:0]  cfg_rdata,
    input  wire         cfg_rd_en
);

    // ── Instantiate ae_interface (which internally instantiates compute_core) ──
    ae_interface u_interface (
        .clk            (clk),
        .rst_n          (rst_n),

        // AXI4-Stream Slave
        .s_axis_tdata   (s_axis_tdata),
        .s_axis_tvalid  (s_axis_tvalid),
        .s_axis_tready  (s_axis_tready),

        // AXI4-Stream Master
        .m_axis_tdata   (m_axis_tdata),
        .m_axis_tvalid  (m_axis_tvalid),
        .m_axis_tready  (m_axis_tready),

        // Config
        .cfg_addr       (cfg_addr),
        .cfg_wdata      (cfg_wdata),
        .cfg_wr_en      (cfg_wr_en),
        .cfg_rdata      (cfg_rdata),
        .cfg_rd_en      (cfg_rd_en)
    );

endmodule

project/m4/tb/tb_top.v
// ============================================================================
// tb_trained_weights.v — End-to-End Test with Real QAT-Trained Weights
// ============================================================================
// Loads 1,352 trained INT8 weights from hex file, streams 8 real sensor
// samples (4 normal + 4 anomaly), and verifies anomaly flag matches
// the Python reference model. This proves the full pipeline:
//   Train in Python -> export INT8 weights -> load into chip -> correct inference
//
// Expected results (from Python hw_ref):
//   Sample 0 (normal):  MSE_q88 =    68, flag = 0
//   Sample 1 (normal):  MSE_q88 =    86, flag = 0
//   Sample 2 (normal):  MSE_q88 =   101, flag = 0
//   Sample 3 (normal):  MSE_q88 =    98, flag = 0
//   Sample 4 (anomaly): MSE_q88 = 11250, flag = 1
//   Sample 5 (anomaly): MSE_q88 = 11001, flag = 1
//   Sample 6 (anomaly): MSE_q88 = 11784, flag = 1
//   Sample 7 (anomaly): MSE_q88 = 11350, flag = 1
// ============================================================================
`timescale 1ns / 1ps

module tb_trained_weights;

    parameter N_WEIGHTS = 1352;
    parameter N_SAMPLES = 8;
    parameter THRESHOLD = 4836;

    reg         clk, rst_n;
    reg [255:0] s_axis_tdata;
    reg         s_axis_tvalid;
    wire        s_axis_tready;
    wire [31:0] m_axis_tdata;
    wire        m_axis_tvalid;
    reg         m_axis_tready;
    reg  [3:0]  cfg_addr;
    reg  [31:0] cfg_wdata;
    reg         cfg_wr_en, cfg_rd_en;
    wire [31:0] cfg_rdata;

    reg [7:0] weights [0:N_WEIGHTS-1];
    reg [7:0] samples [0:N_SAMPLES*32-1];
    reg expected_flag [0:N_SAMPLES-1];

    integer i, j, cycle_count, pass_count, fail_count, sample_num;
    reg [31:0] result_data;
    reg got_flag;
    reg [15:0] got_mse;

    top dut (
        .clk(clk), .rst_n(rst_n),
        .s_axis_tdata(s_axis_tdata), .s_axis_tvalid(s_axis_tvalid),
        .s_axis_tready(s_axis_tready),
        .m_axis_tdata(m_axis_tdata), .m_axis_tvalid(m_axis_tvalid),
        .m_axis_tready(m_axis_tready),
        .cfg_addr(cfg_addr), .cfg_wdata(cfg_wdata),
        .cfg_wr_en(cfg_wr_en), .cfg_rdata(cfg_rdata), .cfg_rd_en(cfg_rd_en)
    );

    initial clk = 0;
    always #5 clk = ~clk;

    task cfg_write(input [3:0] addr, input [31:0] data);
        begin
            @(posedge clk);
            cfg_addr <= addr; cfg_wdata <= data; cfg_wr_en <= 1'b1;
            @(posedge clk);
            cfg_wr_en <= 1'b0;
        end
    endtask

    task load_weight(input [10:0] addr, input [7:0] data);
        begin
            cfg_write(4'h0, {24'd0, data});
            cfg_write(4'h1, {21'd0, addr});
            cfg_write(4'h2, 32'd1);
        end
    endtask

    initial begin
        expected_flag[0] = 0; expected_flag[1] = 0;
        expected_flag[2] = 0; expected_flag[3] = 0;
        expected_flag[4] = 1; expected_flag[5] = 1;
        expected_flag[6] = 1; expected_flag[7] = 1;

        pass_count = 0; fail_count = 0;
        s_axis_tdata = 0; s_axis_tvalid = 0; m_axis_tready = 0;
        cfg_addr = 0; cfg_wdata = 0; cfg_wr_en = 0; cfg_rd_en = 0;

        $readmemh("trained_weights.hex", weights);
        $readmemh("test_samples.hex", samples);

        rst_n = 0;
        repeat (5) @(posedge clk);
        rst_n = 1;
        repeat (2) @(posedge clk);

        $display("============================================================");
        $display("  Trained Weight Integration Test");
        $display("  1,352 QAT-trained INT8 weights + 8 real sensor samples");
        $display("  Threshold = %0d (Q8.8)", THRESHOLD);
        $display("============================================================");

        $display("\n--- Loading %0d trained weights via config port ---", N_WEIGHTS);
        for (i = 0; i < N_WEIGHTS; i = i + 1)
            load_weight(i, weights[i]);
        $display("  Done.");

        $display("\n--- Setting threshold = %0d ---", THRESHOLD);
        cfg_write(4'h3, THRESHOLD);

        $display("\n--- Running %0d samples ---", N_SAMPLES);
        $display("  Sample | Type    | Flag | MSE(Q8.8) | Result");
        $display("  -------+---------+------+-----------+-------");

        for (sample_num = 0; sample_num < N_SAMPLES; sample_num = sample_num + 1) begin
            for (j = 0; j < 32; j = j + 1)
                s_axis_tdata[j*8 +: 8] = samples[sample_num * 32 + j];

            @(posedge clk);
            s_axis_tvalid <= 1'b1;
            @(posedge clk);
            while (!s_axis_tready) @(posedge clk);
            @(posedge clk);
            s_axis_tvalid <= 1'b0;

            m_axis_tready <= 1'b1;
            cycle_count = 0;
            while (!m_axis_tvalid && cycle_count < 10000) begin
                @(posedge clk);
                cycle_count = cycle_count + 1;
            end

            if (cycle_count >= 10000) begin
                $display("  %0d      | TIMEOUT |      |           | FAIL", sample_num);
                fail_count = fail_count + 1;
            end else begin
                result_data = m_axis_tdata;
                got_flag = result_data[0];
                got_mse = result_data[16:1];
                m_axis_tready <= 1'b0;
                @(posedge clk);

                if (got_flag == expected_flag[sample_num]) begin
                    $display("  %0d      | %s |  %0d   | %5d     | PASS",
                        sample_num,
                        (sample_num < 4) ? "NORMAL " : "ANOMALY",
                        got_flag, got_mse);
                    pass_count = pass_count + 1;
                end else begin
                    $display("  %0d      | %s |  %0d   | %5d     | FAIL (expected %0d)",
                        sample_num,
                        (sample_num < 4) ? "NORMAL " : "ANOMALY",
                        got_flag, got_mse, expected_flag[sample_num]);
                    fail_count = fail_count + 1;
                end
            end
        end

        $display("\n============================================================");
        $display("  Results: %0d passed, %0d failed out of %0d", pass_count, fail_count, N_SAMPLES);
        if (fail_count == 0)
            $display("  >>> PASS — Trained weights produce correct anomaly detection <<<");
        else
            $display("  >>> FAIL <<<");
        $display("============================================================");

        #100; $finish;
    end

    initial begin
        $dumpfile("trained_weights.vcd");
        $dumpvars(0, tb_trained_weights);
    end

endmodule

project/m4/sim/final_run.vcd
$date
	Fri Jun  5 05:20:41 2026
$end
$version
	Icarus Verilog
$end
$timescale
	1ps
$end
$scope module tb_trained_weights $end
$var wire 1 ! s_axis_tready $end
$var wire 1 " m_axis_tvalid $end
$var wire 32 # m_axis_tdata [31:0] $end
$var wire 32 $ cfg_rdata [31:0] $end
$var parameter 32 % N_SAMPLES $end
$var parameter 32 & N_WEIGHTS $end
$var parameter 32 ' THRESHOLD $end
$var reg 4 ( cfg_addr [3:0] $end
$var reg 1 ) cfg_rd_en $end
$var reg 32 * cfg_wdata [31:0] $end
$var reg 1 + cfg_wr_en $end
$var reg 1 , clk $end
$var reg 1 - got_flag $end
$var reg 16 . got_mse [15:0] $end
$var reg 1 / m_axis_tready $end
$var reg 32 0 result_data [31:0] $end
$var reg 1 1 rst_n $end
$var reg 256 2 s_axis_tdata [255:0] $end
$var reg 1 3 s_axis_tvalid $end
$var integer 32 4 cycle_count [31:0] $end
$var integer 32 5 fail_count [31:0] $end
$var integer 32 6 i [31:0] $end
$var integer 32 7 j [31:0] $end
$var integer 32 8 pass_count [31:0] $end
$var integer 32 9 sample_num [31:0] $end
$scope module dut $end
$var wire 4 : cfg_addr [3:0] $end
$var wire 1 ) cfg_rd_en $end
$var wire 32 ; cfg_wdata [31:0] $end
$var wire 1 + cfg_wr_en $end
$var wire 1 , clk $end
$var wire 1 / m_axis_tready $end
$var wire 1 1 rst_n $end
$var wire 256 < s_axis_tdata [255:0] $end
$var wire 1 3 s_axis_tvalid $end
$var wire 1 ! s_axis_tready $end
$var wire 1 " m_axis_tvalid $end
$var wire 32 = m_axis_tdata [31:0] $end
$var wire 32 > cfg_rdata [31:0] $end
$scope module u_interface $end
$var wire 4 ? cfg_addr [3:0] $end
$var wire 1 ) cfg_rd_en $end
$var wire 32 @ cfg_wdata [31:0] $end
$var wire 1 + cfg_wr_en $end
$var wire 1 , clk $end
$var wire 32 A m_axis_tdata [31:0] $end
$var wire 1 / m_axis_tready $end
$var wire 1 " m_axis_tvalid $end
$var wire 1 1 rst_n $end
$var wire 256 B s_axis_tdata [255:0] $end
$var wire 1 3 s_axis_tvalid $end
$var wire 1 ! s_axis_tready $end
$var wire 16 C core_mse [15:0] $end
$var wire 1 D core_done $end
$var wire 1 E core_anomaly $end
$var reg 256 F captured_input [255:0] $end
$var reg 32 G cfg_rdata [31:0] $end
$var reg 1 H input_ready $end
$var reg 32 I out_data [31:0] $end
$var reg 1 J out_valid $end
$var reg 16 K reg_threshold [15:0] $end
$var reg 11 L reg_weight_addr [10:0] $end
$var reg 8 M reg_weight_data [7:0] $end
$var reg 1 N reg_weight_wr $end
$var reg 1 O running $end
$scope module u_core $end
$var wire 8 P a_val [7:0] $end
$var wire 1 , clk $end
$var wire 256 Q input_data [255:0] $end
$var wire 1 1 rst_n $end
$var wire 1 H start $end
$var wire 16 R threshold [15:0] $end
$var wire 11 S weight_wr_addr [10:0] $end
$var wire 8 T weight_wr_data [7:0] $end
$var wire 1 N weight_wr_en $end
$var wire 11 U wa7 [10:0] $end
$var wire 11 V wa6 [10:0] $end
$var wire 11 W wa5 [10:0] $end
$var wire 11 X wa4 [10:0] $end
$var wire 11 Y wa3 [10:0] $end
$var wire 11 Z wa2 [10:0] $end
$var wire 11 [ wa1 [10:0] $end
$var wire 11 \ wa0 [10:0] $end
$var wire 6 ] nbase [5:0] $end
$var wire 18 ^ mse_sq [17:0] $end
$var wire 9 _ mse_diff [8:0] $end
$var wire 11 ` ba7 [10:0] $end
$var wire 11 a ba6 [10:0] $end
$var wire 11 b ba5 [10:0] $end
$var wire 11 c ba4 [10:0] $end
$var wire 11 d ba3 [10:0] $end
$var wire 11 e ba2 [10:0] $end
$var wire 11 f ba1 [10:0] $end
$var wire 11 g ba0 [10:0] $end
$var parameter 3 h S_BIAS $end
$var parameter 3 i S_COPY $end
$var parameter 3 j S_DONE $end
$var parameter 3 k S_IDLE $end
$var parameter 3 l S_LOAD $end
$var parameter 3 m S_MAC $end
$var parameter 3 n S_MSE $end
$var reg 32 o acc0 [31:0] $end
$var reg 32 p acc1 [31:0] $end
$var reg 32 q acc2 [31:0] $end
$var reg 32 r acc3 [31:0] $end
$var reg 32 s acc4 [31:0] $end
$var reg 32 t acc5 [31:0] $end
$var reg 32 u acc6 [31:0] $end
$var reg 32 v acc7 [31:0] $end
$var reg 1 E anomaly_flag $end
$var reg 32 w bv [31:0] $end
$var reg 2 x cur_layer [1:0] $end
$var reg 3 y cur_round [2:0] $end
$var reg 1 D done $end
$var reg 11 z l_bbase [10:0] $end
$var reg 6 { l_in [5:0] $end
$var reg 6 | l_out [5:0] $end
$var reg 1 } l_relu $end
$var reg 3 ~ l_rounds [2:0] $end
$var reg 11 !" l_wbase [10:0] $end
$var reg 6 "" mac_idx [5:0] $end
$var reg 32 #" mse_acc [31:0] $end
$var reg 6 $" mse_idx [5:0] $end
$var reg 16 %" mse_out [15:0] $end
$var reg 8 &" r0 [7:0] $end
$var reg 8 '" r1 [7:0] $end
$var reg 8 (" r2 [7:0] $end
$var reg 8 )" r3 [7:0] $end
$var reg 8 *" r4 [7:0] $end
$var reg 8 +" r5 [7:0] $end
$var reg 8 ," r6 [7:0] $end
$var reg 8 -" r7 [7:0] $end
$var reg 3 ." state [2:0] $end
$var integer 32 /" k [31:0] $end
$upscope $end
$upscope $end
$upscope $end
$scope task cfg_write $end
$var reg 4 0" addr [3:0] $end
$var reg 32 1" data [31:0] $end
$upscope $end
$scope task load_weight $end
$var reg 11 2" addr [10:0] $end
$var reg 8 3" data [7:0] $end
$upscope $end
$upscope $end
$enddefinitions $end
$comment Show the parameter values. $end
$dumpall
b100 n
b10 m
b1 l
b0 k
b101 j
b110 i
b11 h
b1001011100100 '
b10101001000 &
b1000 %
$end
#0
$dumpvars
bx 3"
bx 2"
bx 1"
bx 0"
b100000 /"
b0 ."
bx -"
bx ,"
bx +"
bx *"
bx )"
bx ("
bx '"
bx &"
b0 %"
b0 $"
b0 #"
b0 ""
b0 !"
b10 ~
1}
b10000 |
b100000 {
b1000000000 z
b0 y
b0 x
bx w
b0 v
b0 u
b0 t
b0 s
b0 r
b0 q
b0 p
b0 o
b1000000000 g
b1000000001 f
b1000000010 e
b1000000011 d
b1000000100 c
b1000000101 b
b1000000110 a
b1000000111 `
b0 _
b0 ^
b0 ]
b0 \
b100000 [
b1000000 Z
b1100000 Y
b10000000 X
b10100000 W
b11000000 V
b11100000 U
b0 T
b0 S
b100000000 R
b0 Q
b0 P
0O
0N
b0 M
b0 L
b100000000 K
0J
b0 I
0H
b11011110101011011011111011101111 G
b0 F
0E
0D
b0 C
b0 B
b0 A
b0 @
b0 ?
b11011110101011011011111011101111 >
b0 =
b0 <
b0 ;
b0 :
bx 9
b0 8
bx 7
bx 6
b0 5
bx 4
03
b0 2
01
bx 0
0/
bx .
x-
0,
0+
b0 *
0)
b0 (
b11011110101011011011111011101111 $
b0 #
0"
1!
$end
#5000
b100000 /"
1,
#10000
0,
#15000
b100000 /"
1,
#20000
0,
#25000
b100000 /"
1,
#30000
0,
#35000
b100000 /"
1,
#40000
0,
#45000
11
1,
#50000
0,
#55000
1,
#60000
0,
#65000
b1 1"
b0 0"
b1 3"
b0 2"
b0 6
1,
#70000
0,
#75000
1+
b1 *
b1 ;
b1 @
1,
#80000
0,
#85000
b1 M
b1 T
0+
b0 1"
b1 0"
1,
#90000
0,
#95000
1+
b0 *
b0 ;
b0 @
b1 (
b1 :
b1 ?
1,
#100000
0,
#105000
0+
b1 1"
b10 0"
1,
#110000
0,
#115000
1+
b1 *
b1 ;
b1 @
b10 (
b10 :
b10 ?
1,
#120000
0,
#125000
1N
0+
b0 0"
b1 2"
b1 6
1,
#130000
0,
#135000
0N
1+
b0 (
b0 :
b0 ?
1,
#140000
0,
#145000
0+
b1 0"
1,
#150000
0,
#155000
1+
b1 (
b1 :
b1 ?
1,
#160000
0,
#165000
b1 L
b1 S
0+
b10 0"
1,
#170000
0,
#175000
1+
b10 (
b10 :
b10 ?
1,
#180000
0,
#185000
1N
0+
b11111110 1"
b0 0"
b11111110 3"
b10 2"
b10 6
1,
#190000
0,
#195000
0N
1+
b11111110 *
b11111110 ;
b11111110 @
b0 (
b0 :
b0 ?
1,
#200000
0,
#205000
b11111110 M
b11111110 T
0+
b10 1"
b1 0"
1,
#210000
0,
#215000
1+
b10 *
b10 ;
b10 @
b1 (
b1 :
b1 ?
1,
#220000
0,
#225000
b10 L
b10 S
0+
b1 1"
b10 0"
1,
#230000
0,
#235000
1+
b1 *
b1 ;
b1 @
b10 (
b10 :
b10 ?
1,
#240000
0,
#245000
1N
0+
b11 1"
b0 0"
b11 3"
b11 2"
b11 6
1,
#250000
0,
#255000
0N
1+
b11 *
b11 ;
b11 @
b0 (
b0 :
b0 ?
1,
#260000
0,
#265000
b11 M
b11 T
0+
b1 0"
1,
#270000
0,
#275000
1+
b1 (
b1 :
b1 ?
1,
#280000
0,
#285000
b11 L
b11 S
0+
b1 1"
b10 0"
1,
#290000
0,
#295000
1+
b1 *
b1 ;
b1 @
b10 (
b10 :
b10 ?
1,
#300000
0,
#305000
1N
0+
b11 1"
b0 0"
b100 2"
b100 6
1,
#310000
0,
#315000
0N
1+
b11 *
b11 ;
b11 @
b0 (
b0 :
b0 ?
1,
#320000
0,
#325000
0+
b100 1"
b1 0"
1,
#330000
0,
